pydatalens/__init__.py
pydatalens/cleaning.py
pydatalens/eda.py
pydatalens/utils.py
pydatalens/visualizations.py
tests/__init__.py
tests/test_cleaning.py
tests/test_eda.py
tests/test_visualizations.py
PyDataLens-0.3.dist-info/LICENSE.txt
PyDataLens-0.3.dist-info/METADATA
PyDataLens-0.3.dist-info/WHEEL
PyDataLens-0.3.dist-info/top_level.txt
PyDataLens-0.3.dist-info/RECORD
